test_plus/__init__.py
test_plus/compat.py
test_plus/plugin.py
test_plus/runner.py
test_plus/status_codes.py
test_plus/test.py
django_test_plus-2.4.1.dist-info/METADATA
django_test_plus-2.4.1.dist-info/WHEEL
django_test_plus-2.4.1.dist-info/entry_points.txt
django_test_plus-2.4.1.dist-info/licenses/AUTHORS.txt
django_test_plus-2.4.1.dist-info/licenses/LICENSE
django_test_plus-2.4.1.dist-info/RECORD
