Metadata-Version: 2.4
Name: django-test-plus
Version: 2.4.1
Summary: django-test-plus provides useful additions to Django's default TestCase
Project-URL: Changelog, https://github.com/revsys/django-test-plus/blob/main/CHANGELOG.md
Project-URL: Homepage, https://github.com/revsys/django-test-plus/
Author-email: Frank Wiles <frank@revsys.com>, Jeff Triplett <jeff@revsys.com>
License-File: AUTHORS.txt
License-File: LICENSE
Classifier: Development Status :: 5 - Production/Stable
Classifier: Environment :: Web Environment
Classifier: Framework :: Django
Classifier: Framework :: Django :: 4.2
Classifier: Framework :: Django :: 5.0
Classifier: Framework :: Django :: 5.1
Classifier: Framework :: Django :: 5.2
Classifier: Framework :: Django :: 6.0
Classifier: Framework :: Pytest
Classifier: Intended Audience :: Developers
Classifier: License :: OSI Approved :: BSD License
Classifier: Operating System :: OS Independent
Classifier: Programming Language :: Python :: 3
Classifier: Programming Language :: Python :: 3.10
Classifier: Programming Language :: Python :: 3.11
Classifier: Programming Language :: Python :: 3.12
Classifier: Programming Language :: Python :: 3.13
Classifier: Programming Language :: Python :: 3.14
Requires-Python: >=3.10
Requires-Dist: packaging
Provides-Extra: docs
Requires-Dist: furo; extra == 'docs'
Requires-Dist: sphinx; extra == 'docs'
Requires-Dist: sphinx-copybutton; extra == 'docs'
Requires-Dist: sphinx-prompt; extra == 'docs'
Provides-Extra: lint
Requires-Dist: pre-commit; extra == 'lint'
Provides-Extra: test
Requires-Dist: factory-boy; extra == 'test'
Requires-Dist: pytest; extra == 'test'
Requires-Dist: pytest-cov; extra == 'test'
Requires-Dist: pytest-django; extra == 'test'
Provides-Extra: testing
Requires-Dist: factory-boy; extra == 'testing'
Requires-Dist: pytest; extra == 'testing'
Requires-Dist: pytest-cov; extra == 'testing'
Requires-Dist: pytest-django; extra == 'testing'
